lightning_thunder-0.2.6.dist-info/licenses/LICENSE
thunder/__about__.py
thunder/__init__.py
thunder/common.py
thunder/py.typed
thunder/benchmarks/__init__.py
thunder/benchmarks/benchmark_hf.py
thunder/benchmarks/benchmark_inference.py
thunder/benchmarks/benchmark_litgpt.py
thunder/benchmarks/benchmark_peft.py
thunder/benchmarks/conftest.py
thunder/benchmarks/distributed.py
thunder/benchmarks/einsum.py
thunder/benchmarks/layers_for_inference_benchmark.py
thunder/benchmarks/targets.py
thunder/benchmarks/test_benchmark_litgpt.py
thunder/benchmarks/utils.py
thunder/clang/__init__.py
thunder/clang/langctx.py
thunder/clang/utils.py
thunder/core/__init__.py
thunder/core/baseutils.py
thunder/core/codeutils.py
thunder/core/compile_data.py
thunder/core/devices.py
thunder/core/dtypes.py
thunder/core/interpreter.py
thunder/core/jit_ext.py
thunder/core/langctxs.py
thunder/core/module.py
thunder/core/options.py
thunder/core/patterns.py
thunder/core/prims.py
thunder/core/profile.py
thunder/core/proxies.py
thunder/core/pytree.py
thunder/core/recipe.py
thunder/core/rematerialization.py
thunder/core/symbol.py
thunder/core/trace.py
thunder/core/trace_interpreter.py
thunder/core/transform_common.py
thunder/core/transforms.py
thunder/core/update_aliases.py
thunder/core/utils.py
thunder/core/vjp_utils.py
thunder/dev_utils/__init__.py
thunder/dev_utils/benchmark.py
thunder/dev_utils/check_trace.py
thunder/dev_utils/debug_transform.py
thunder/dev_utils/nvtx_profile_transform.py
thunder/dev_utils/profile_transform.py
thunder/dev_utils/utils.py
thunder/distributed/__init__.py
thunder/distributed/bucketing.py
thunder/distributed/checkpoint.py
thunder/distributed/prims.py
thunder/distributed/utils.py
thunder/distributed/tensor_parallel/__init__.py
thunder/distributed/tensor_parallel/column_wise.py
thunder/distributed/tensor_parallel/common.py
thunder/distributed/tensor_parallel/optimize_comm.py
thunder/distributed/tensor_parallel/row_wise.py
thunder/distributed/transforms/__init__.py
thunder/distributed/transforms/ddp.py
lightning_thunder-0.2.6.dist-info/METADATA
lightning_thunder-0.2.6.dist-info/WHEEL
lightning_thunder-0.2.6.dist-info/top_level.txt
lightning_thunder-0.2.6.dist-info/RECORD
