Metadata-Version: 2.4
Name: lightning-thunder
Version: 0.2.6
Summary: Lightning Thunder is a source-to-source compiler for PyTorch, enabling PyTorch programs to run on different hardware accelerators and graph compilers.
Author-email: Lightning AI <support@lightning.ai>
License-Expression: Apache-2.0
Project-URL: Homepage, https://github.com/Lightning-AI/lightning-thunder
Project-URL: Bug Tracker, https://github.com/Lightning-AI/lightning-thunder/issues
Project-URL: Documentation, https://lightning-thunder.rtfd.io/en/latest/
Project-URL: Source, https://github.com/Lightning-AI/lightning-thunder
Keywords: deep learning,AI,compiler
Classifier: Environment :: Console
Classifier: Natural Language :: English
Classifier: Development Status :: 3 - Alpha
Classifier: Intended Audience :: Developers
Classifier: Topic :: Scientific/Engineering :: Artificial Intelligence
Classifier: Topic :: Scientific/Engineering :: Information Analysis
Classifier: Operating System :: OS Independent
Classifier: Programming Language :: Python :: 3
Classifier: Programming Language :: Python :: 3.10
Classifier: Programming Language :: Python :: 3.11
Classifier: Programming Language :: Python :: 3.12
Classifier: Programming Language :: Python :: 3.13
Requires-Python: <3.14,>=3.10
License-File: LICENSE
Requires-Dist: torch>=2.7.1
Requires-Dist: looseversion==1.3.0
Requires-Dist: lightning-utilities>0.7.0
Requires-Dist: numpy
Requires-Dist: networkx>=3.3
Requires-Dist: optree>=0.12.1
Requires-Dist: opt_einsum>=3.3.0
Requires-Dist: mpmath<1.4.0
Requires-Dist: dill>=0.3.8
Dynamic: description
Dynamic: description-content-type
Dynamic: license-file
Dynamic: requires-dist
